{"title":"Body","body":{"required":true,"content":{"application/json":{"schema":{"type":"object","properties":{"type":{"type":"string","enum":["email","sms"]},"message":{"type":"string","format":"email"},"subject":{"type":"string"},"registration_id":{"description":"Required if sending only single message","type":"integer"},"params":{"type":"array","items":{"type":"object","description":"Same parameters as when filtering registrations","properties":{"advanced_search":{"type":"boolean"},"schedule_id":{"type":"integer"},"course_id":{"type":"integer"},"place_id":{"type":"integer"},"room_id":{"type":"integer"},"trainer_id":{"type":"integer"},"billing_period_id":{"type":"integer"},"billing_status":{"type":"string","enum":["paid","unpaid","partially_paid","overpaid"],"title":"Prop_Billing_Status"},"user":{"type":"string"},"user_id":{"type":"integer"},"email":{"type":"string"},"registration_id":{"type":"integer"},"exclude":{"type":"string"},"exclude_user":{"type":"string"},"order_id":{"type":"integer"},"parent":{"type":"integer"},"distinct":{"type":"boolean"},"payment_id":{"type":"integer"},"inactive_customers":{"type":"boolean"},"marketing_messages":{"type":"boolean"},"ef_full_name":{"type":"string"},"status":{"type":"string"},"created_from":{"type":"string"},"created_to":{"type":"string"},"schedule_groups":{"type":"string"},"schedule_query":{"type":"string"}}}}}}}}}}